firemon.py
firemon-0.4.1.dist-info/DESCRIPTION.rst
firemon-0.4.1.dist-info/METADATA
firemon-0.4.1.dist-info/RECORD
firemon-0.4.1.dist-info/WHEEL
firemon-0.4.1.dist-info/entry_points.txt
firemon-0.4.1.dist-info/metadata.json
firemon-0.4.1.dist-info/top_level.txt
