Metadata-Version: 2.0
Name: firemon
Version: 0.4.1
Summary: UNKNOWN
Home-page: UNKNOWN
Author: UNKNOWN
Author-email: UNKNOWN
License: UNKNOWN
Platform: UNKNOWN
Requires-Dist: psutil
Requires-Dist: python-slugify
Requires-Dist: requests
